ToolBoxByHanXu/__init__.py
ToolBoxByHanXu/image_spider/__init__.py
ToolBoxByHanXu/image_spider/baidu/__init__.py
ToolBoxByHanXu/image_spider/bing/__init__.py
ToolBoxByHanXu/image_spider/pixiv/__init__.py
ToolBoxByHanXu/normalize_md/__init__.py
ToolBoxByHanXu/rename_files/__init__.py
ToolBoxByHanXu-1.0.2.dist-info/LICENSE
ToolBoxByHanXu-1.0.2.dist-info/METADATA
ToolBoxByHanXu-1.0.2.dist-info/WHEEL
ToolBoxByHanXu-1.0.2.dist-info/top_level.txt
ToolBoxByHanXu-1.0.2.dist-info/RECORD
